libsigopt/aux/__init__.py
libsigopt/aux/adapter_info_containers.py
libsigopt/aux/constant.py
libsigopt/aux/errors.py
libsigopt/aux/geometry_utils.py
libsigopt/aux/multimetric.py
libsigopt/aux/samplers.py
libsigopt/aux/utils.py
libsigopt/aux/validate_schema.py
libsigopt/compute/__init__.py
libsigopt/compute/acquisition_function.py
libsigopt/compute/acquisition_function_optimization.py
libsigopt/compute/covariance.py
libsigopt/compute/covariance_base.py
libsigopt/compute/domain.py
libsigopt/compute/expected_improvement.py
libsigopt/compute/gaussian_process.py
libsigopt/compute/gaussian_process_sum.py
libsigopt/compute/log_likelihood.py
libsigopt/compute/multitask_acquisition_function.py
libsigopt/compute/multitask_covariance.py
libsigopt/compute/optimization.py
libsigopt/compute/optimization_auxiliary.py
libsigopt/compute/predictor.py
libsigopt/compute/probabilistic_failures.py
libsigopt/compute/python_utils.py
libsigopt/compute/search.py
libsigopt/compute/sigopt_parzen_estimator.py
libsigopt/compute/vectorized_optimizers.py
libsigopt/compute/misc/__init__.py
libsigopt/compute/misc/constant.py
libsigopt/compute/misc/data_containers.py
libsigopt/compute/misc/multimetric.py
libsigopt/views/__init__.py
libsigopt/views/view.py
libsigopt/views/rest/__init__.py
libsigopt/views/rest/gp_ei_categorical.py
libsigopt/views/rest/gp_hyper_opt_multimetric.py
libsigopt/views/rest/gp_next_points_categorical.py
libsigopt/views/rest/multisolution_best_assignments.py
libsigopt/views/rest/random_search_next_points.py
libsigopt/views/rest/search_next_points.py
libsigopt/views/rest/spe_next_points.py
libsigopt/views/rest/spe_search_next_points.py
libsigopt-1.0.0.dist-info/LICENSE
libsigopt-1.0.0.dist-info/METADATA
libsigopt-1.0.0.dist-info/WHEEL
libsigopt-1.0.0.dist-info/top_level.txt
libsigopt-1.0.0.dist-info/RECORD
